odoo/addons/tms/README.rst
odoo/addons/tms/__init__.py
odoo/addons/tms/__manifest__.py
odoo/addons/tms/data/ir_sequence_data.xml
odoo/addons/tms/data/module_category.xml
odoo/addons/tms/data/tms_stage.xml
odoo/addons/tms/data/tms_team.xml
odoo/addons/tms/data/uom_category.xml
odoo/addons/tms/demo/res_partner.xml
odoo/addons/tms/demo/tms_crew.xml
odoo/addons/tms/demo/tms_driver.xml
odoo/addons/tms/demo/tms_order.xml
odoo/addons/tms/demo/tms_route.xml
odoo/addons/tms/demo/tms_team.xml
odoo/addons/tms/i18n/it.po
odoo/addons/tms/i18n/pt_BR.po
odoo/addons/tms/i18n/tms.pot
odoo/addons/tms/models/__init__.py
odoo/addons/tms/models/fleet_vehicle.py
odoo/addons/tms/models/res_config_settings.py
odoo/addons/tms/models/res_partner.py
odoo/addons/tms/models/tms_crew.py
odoo/addons/tms/models/tms_driver.py
odoo/addons/tms/models/tms_insurance.py
odoo/addons/tms/models/tms_order.py
odoo/addons/tms/models/tms_route.py
odoo/addons/tms/models/tms_stage.py
odoo/addons/tms/models/tms_team.py
odoo/addons/tms/readme/CONFIGURE.md
odoo/addons/tms/readme/CONTRIBUTORS.md
odoo/addons/tms/readme/CREDITS.md
odoo/addons/tms/readme/DESCRIPTION.md
odoo/addons/tms/readme/MAINTAINERS.md
odoo/addons/tms/readme/USAGE.md
odoo/addons/tms/security/ir.model.access.csv
odoo/addons/tms/security/ir_rule.xml
odoo/addons/tms/security/res_groups.xml
odoo/addons/tms/static/description/icon.png
odoo/addons/tms/static/description/icon.svg
odoo/addons/tms/static/description/index.html
odoo/addons/tms/tests/__init__.py
odoo/addons/tms/tests/test_fleet_vehicle.py
odoo/addons/tms/tests/test_res_partner.py
odoo/addons/tms/tests/test_tms_crew.py
odoo/addons/tms/tests/test_tms_driver.py
odoo/addons/tms/tests/test_tms_order.py
odoo/addons/tms/tests/test_tms_route.py
odoo/addons/tms/tests/test_tms_stage.py
odoo/addons/tms/tests/test_tms_team.py
odoo/addons/tms/views/fleet_menu.xml
odoo/addons/tms/views/fleet_vehicle.xml
odoo/addons/tms/views/menu.xml
odoo/addons/tms/views/res_config_settings.xml
odoo_addon_tms-18.0.1.1.0.28.dist-info/METADATA
odoo_addon_tms-18.0.1.1.0.28.dist-info/WHEEL
odoo_addon_tms-18.0.1.1.0.28.dist-info/top_level.txt
odoo_addon_tms-18.0.1.1.0.28.dist-info/RECORD
