Metadata-Version: 2.1
Name: odoo-addon-tms
Version: 18.0.1.1.0.28
Requires-Python: >=3.10
Requires-Dist: odoo==18.0.*
Summary: Manage Vehicles, Drivers, Routes and Trips
Home-page: https://github.com/OCA/stock-logistics-transport
License: AGPL-3
Author: Open Source Integrators, Odoo Community Association (OCA)
Author-email: support@odoo-community.org
Classifier: Programming Language :: Python
Classifier: Framework :: Odoo
Classifier: Framework :: Odoo :: 18.0
Classifier: License :: OSI Approved :: GNU Affero General Public License v3
Classifier: Development Status :: 3 - Alpha
